{"version":1,"functions":{"/api/achievements":{},"/api/coach/history":{},"/api/nutrition/estimate":{},"/api/coach/chat":{},"/api/nutrition":{},"/api/nutrition/search":{},"/api/plan":{},"/api/nutrition/favorites":{},"/api/progress/measurements":{},"/api/progress/prs":{},"/api/progress/analytics":{},"/api/progress/weekly":{},"/api/subscription/checkout":{},"/api/subscription/webhook":{},"/api/user/onboarding":{},"/api/exercises/swap":{},"/api/workouts/log":{},"/api/workouts/today":{},"/api/nutrition/targets":{},"/api/user/profile":{}}}